{"playlist": {"name": "Soraya - Chevalerie", "id": "spotify:playlist:39yZwL2SZ8mjp8TrroYWRk"}, "tracks": [{"spotifyInfo": {"title": "Beautiful Strangers", "artist": "Kevin Morby", "time": 375903, "min": 6, "sec": 15}, "youtubeInfo": {"id": "/watch?v=OedxVySrU7Q", "URL": "https://www.youtube.com//watch?v=OedxVySrU7Q", "title": "Kevin Morby - Beautiful Strangers (Official Audio)"}}, {"spotifyInfo": {"title": "Lost On You - Live at Harvard and Stone", "artist": "LP", "time": 302070, "min": 5, "sec": 2}, "youtubeInfo": {"id": "/watch?v=wDjeBNv6ip0", "URL": "https://www.youtube.com//watch?v=wDjeBNv6ip0", "title": "LP - Lost On You [Live Session]"}}, {"spotifyInfo": {"title": "You're My Waterloo", "artist": "The Libertines", "time": 259133, "min": 4, "sec": 19}, "youtubeInfo": {"id": "/watch?v=y82uMwGFfVI", "URL": "https://www.youtube.com//watch?v=y82uMwGFfVI", "title": "The Libertines - You're My Waterloo"}}, {"spotifyInfo": {"title": "Summer Wine", "artist": "Nancy Sinatra", "time": 256279, "min": 4, "sec": 16}, "youtubeInfo": {"id": "/watch?v=Ib_eW9VSUwM", "URL": "https://www.youtube.com//watch?v=Ib_eW9VSUwM", "title": "Nancy Sinatra & Lee Hazlewood-Summer Wine"}}, {"spotifyInfo": {"title": "Golden Brown", "artist": "The Stranglers", "time": 206760, "min": 3, "sec": 26}, "youtubeInfo": {"id": "/watch?v=AWAsI3U2EaE", "URL": "https://www.youtube.com//watch?v=AWAsI3U2EaE", "title": "Golden Brown - The Stranglers"}}, {"spotifyInfo": {"title": "Fluorescent Adolescent", "artist": "Arctic Monkeys", "time": 183893, "min": 3, "sec": 3}, "youtubeInfo": {"id": "/watch?v=ma9I9VBKPiw", "URL": "https://www.youtube.com//watch?v=ma9I9VBKPiw", "title": "Arctic Monkeys - Fluorescent Adolescent (Official Video)"}}, {"spotifyInfo": {"title": "Instant Crush (feat. Julian Casablancas)", "artist": "Daft Punk", "time": 337560, "min": 5, "sec": 37}, "youtubeInfo": {"id": "/watch?v=a5uQMwRMHcs", "URL": "https://www.youtube.com//watch?v=a5uQMwRMHcs", "title": "Daft Punk ft. Julian Casablancas - Instant Crush (Official Video)"}}, {"spotifyInfo": {"title": "Mon amie la rose", "artist": "Fran\u00e7oise Hardy", "time": 137160, "min": 2, "sec": 17}, "youtubeInfo": {"id": "/watch?v=2ICFtXx546A", "URL": "https://www.youtube.com//watch?v=2ICFtXx546A", "title": "Fran\u00e7oise Hardy - Mon amie la rose (1965)"}}, {"spotifyInfo": {"title": "Hello, I Love You", "artist": "The Doors", "time": 133200, "min": 2, "sec": 13}, "youtubeInfo": {"id": "/watch?v=8f1z-nHvt3c", "URL": "https://www.youtube.com//watch?v=8f1z-nHvt3c", "title": "The Doors - Hello, I Love You"}}, {"spotifyInfo": {"title": "Veridis Quo", "artist": "Daft Punk", "time": 345186, "min": 5, "sec": 45}, "youtubeInfo": {"id": "/watch?v=ySLc8gZ3oEc", "URL": "https://www.youtube.com//watch?v=ySLc8gZ3oEc", "title": "Daft Punk - Veridis Quo (Music Video)"}}, {"spotifyInfo": {"title": "Roller Disco", "artist": "Jonathan Bree", "time": 138000, "min": 2, "sec": 18}, "youtubeInfo": {"id": "/watch?v=K-OtS8bYqbk", "URL": "https://www.youtube.com//watch?v=K-OtS8bYqbk", "title": "Jonathan Bree - Roller Disco"}}, {"spotifyInfo": {"title": "Yes, Yes, We Are Magicians", "artist": "The Crookes", "time": 190386, "min": 3, "sec": 10}, "youtubeInfo": {"id": "/watch?v=lA3hYdKlDM8", "URL": "https://www.youtube.com//watch?v=lA3hYdKlDM8", "title": "'Yes, Yes, We're Magicians' by The Crookes - Burberry Acoustic"}}, {"spotifyInfo": {"title": "Only Ones Who Know", "artist": "Arctic Monkeys", "time": 184760, "min": 3, "sec": 4}, "youtubeInfo": {"id": "/watch?v=d82zxqZHUo8", "URL": "https://www.youtube.com//watch?v=d82zxqZHUo8", "title": "Arctic Monkeys - Only One Who Knows"}}, {"spotifyInfo": {"title": "Somebody Nobody Wants", "artist": "Dion", "time": 158586, "min": 2, "sec": 38}, "youtubeInfo": {"id": "/watch?v=80h0I3N-WbE", "URL": "https://www.youtube.com//watch?v=80h0I3N-WbE", "title": "Dion - Somebody Nobody Wants"}}, {"spotifyInfo": {"title": "People Are Strange", "artist": "The Doors", "time": 130173, "min": 2, "sec": 10}, "youtubeInfo": {"id": "/watch?v=GJY8jJkDoMY", "URL": "https://www.youtube.com//watch?v=GJY8jJkDoMY", "title": "The Doors - People Are Strange"}}, {"spotifyInfo": {"title": "(Love Is Like A) Heatwave - Mono Version", "artist": "The Supremes", "time": 161507, "min": 2, "sec": 41}, "youtubeInfo": {"id": "/watch?v=so2CjbqGMPQ", "URL": "https://www.youtube.com//watch?v=so2CjbqGMPQ", "title": "The Supremes - (Love Is Like A) Heatwave"}}, {"spotifyInfo": {"title": "There She Goes", "artist": "Babyshambles", "time": 215071, "min": 3, "sec": 35}, "youtubeInfo": {"id": "/watch?v=GJ1gIWNY8M8", "URL": "https://www.youtube.com//watch?v=GJ1gIWNY8M8", "title": "Babyshambles - \"There she goes\" (2007)"}}, {"spotifyInfo": {"title": "Music When The Lights Go Out", "artist": "The Libertines", "time": 182386, "min": 3, "sec": 2}, "youtubeInfo": {"id": "/watch?v=5_jWeyVy0RQ", "URL": "https://www.youtube.com//watch?v=5_jWeyVy0RQ", "title": "The Libertines - Music When the Lights Go Out"}}, {"spotifyInfo": {"title": "Glass in the park", "artist": "Alex Turner", "time": 239653, "min": 3, "sec": 59}, "youtubeInfo": {"id": "/watch?v=2jogmnbvy0U", "URL": "https://www.youtube.com//watch?v=2jogmnbvy0U", "title": "Glass in the park"}}, {"spotifyInfo": {"title": "Valerie (feat. Amy Winehouse) - Version Revisited", "artist": "Mark Ronson", "time": 219413, "min": 3, "sec": 39}, "youtubeInfo": {"id": null, "URL": "#", "title": "NaN"}}, {"spotifyInfo": {"title": "Le temps est bon", "artist": "Bon Entendeur", "time": 210253, "min": 3, "sec": 30}, "youtubeInfo": {"id": "/watch?v=RMWBriHwVrI", "URL": "https://www.youtube.com//watch?v=RMWBriHwVrI", "title": "Bon Entendeur vs Isabelle Pierre - Le Temps Est Bon (Clip Officiel)"}}, {"spotifyInfo": {"title": "It's hard to get around the wind", "artist": "Alex Turner", "time": 247013, "min": 4, "sec": 7}, "youtubeInfo": {"id": "/watch?v=YOZZomkMZLk", "URL": "https://www.youtube.com//watch?v=YOZZomkMZLk", "title": "Alex Turner - It's Hard To Get Around The Wind"}}, {"spotifyInfo": {"title": "Take on me", "artist": "Anni B Sweet", "time": 191280, "min": 3, "sec": 11}, "youtubeInfo": {"id": "/watch?v=GJuwdcQlT1g", "URL": "https://www.youtube.com//watch?v=GJuwdcQlT1g", "title": "ANNI B SWEET- TAKE ON ME"}}, {"spotifyInfo": {"title": "Just Cant Get Enough", "artist": "VASSY", "time": 105493, "min": 1, "sec": 45}, "youtubeInfo": {"id": "/watch?v=W6S-Ku8K37U", "URL": "https://www.youtube.com//watch?v=W6S-Ku8K37U", "title": "VASSY - Just Can't Get Enough [Acoustic]"}}, {"spotifyInfo": {"title": "Clandestino", "artist": "Adriana Calcanhotto", "time": 145773, "min": 2, "sec": 25}, "youtubeInfo": {"id": "/watch?v=mdQIsq_vxdg", "URL": "https://www.youtube.com//watch?v=mdQIsq_vxdg", "title": "Adriana Calcanhotto - Clandestino - V\u00eddeo Oficial"}}, {"spotifyInfo": {"title": "Moi Lolita", "artist": "Julien Dor\u00e9", "time": 256026, "min": 4, "sec": 16}, "youtubeInfo": {"id": "/watch?v=fMQw7WldCfE", "URL": "https://www.youtube.com//watch?v=fMQw7WldCfE", "title": "Julien Dor\u00e9 - Moi... Lolita (Clip officiel)"}}, {"spotifyInfo": {"title": "Girl On Fire", "artist": "jo.sco", "time": 200075, "min": 3, "sec": 20}, "youtubeInfo": {"id": "/watch?v=xvJZuqHQhpo", "URL": "https://www.youtube.com//watch?v=xvJZuqHQhpo", "title": "Girl On Fire"}}, {"spotifyInfo": {"title": "Hip Hop Mash Up", "artist": "L.E.J", "time": 180186, "min": 3, "sec": 0}, "youtubeInfo": {"id": "/watch?v=lvoz-fSze8s", "URL": "https://www.youtube.com//watch?v=lvoz-fSze8s", "title": "L.E.J - HIP-HOP MASHUP"}}, {"spotifyInfo": {"title": "I Just Can't Get You Out Of My Head", "artist": "H\u00e9l\u00e8na", "time": 277386, "min": 4, "sec": 37}, "youtubeInfo": {"id": null, "URL": "#", "title": "NaN"}}, {"spotifyInfo": {"title": "Heathens", "artist": "Tana\u00eb", "time": 216986, "min": 3, "sec": 36}, "youtubeInfo": {"id": "/watch?v=NFZYMJIDPbI", "URL": "https://www.youtube.com//watch?v=NFZYMJIDPbI", "title": "Twenty One Pilots - Heathens / cover by Tana\u00eb"}}, {"spotifyInfo": {"title": "Balance ton quoi", "artist": "Ang\u00e8le", "time": 189480, "min": 3, "sec": 9}, "youtubeInfo": {"id": "/watch?v=Hi7Rx3En7-k", "URL": "https://www.youtube.com//watch?v=Hi7Rx3En7-k", "title": "Ang\u00e8le - Balance Ton Quoi [CLIP OFFICIEL]"}}, {"spotifyInfo": {"title": "Instant crush - Live from Spotify Paris", "artist": "The D\u00f8", "time": 211227, "min": 3, "sec": 31}, "youtubeInfo": {"id": "/watch?v=JEU0tGpEqKU", "URL": "https://www.youtube.com//watch?v=JEU0tGpEqKU", "title": "The Do en live dans Le Lab Virgin Radio - \"Instant Crush\""}}, {"spotifyInfo": {"title": "Carnival of the Animals, R. 125: The Swan", "artist": "Camille Saint-Sa\u00ebns", "time": 184706, "min": 3, "sec": 4}, "youtubeInfo": {"id": "/watch?v=qzbi3QCzdpg", "URL": "https://www.youtube.com//watch?v=qzbi3QCzdpg", "title": "Carnival of the Animals, R. 125: XIII. The Swan"}}, {"spotifyInfo": {"title": "Ayayay", "artist": "Bratia Stereo", "time": 111263, "min": 1, "sec": 51}, "youtubeInfo": {"id": "/watch?v=XVfZT7CKIb0", "URL": "https://www.youtube.com//watch?v=XVfZT7CKIb0", "title": "Bratia Stereo - Ayayay (ft. Tony Tonite)"}}, {"spotifyInfo": {"title": "Sonate pacifique", "artist": "L'Imp\u00e9ratrice", "time": 348944, "min": 5, "sec": 48}, "youtubeInfo": {"id": "/watch?v=jiRUH9b33dA", "URL": "https://www.youtube.com//watch?v=jiRUH9b33dA", "title": "L'Imp\u00e9ratrice \u2014 SONATE PACIFIQUE"}}, {"spotifyInfo": {"title": "Together", "artist": "The Raconteurs", "time": 238200, "min": 3, "sec": 58}, "youtubeInfo": {"id": "/watch?v=zFBZFcjiCU8", "URL": "https://www.youtube.com//watch?v=zFBZFcjiCU8", "title": "The Raconteurs Together"}}, {"spotifyInfo": {"title": "Amoureux solitaires", "artist": "Lio", "time": 221800, "min": 3, "sec": 41}, "youtubeInfo": {"id": "/watch?v=IblzIxNlk3Q", "URL": "https://www.youtube.com//watch?v=IblzIxNlk3Q", "title": "Lio / Amoureux solitaires / 1980"}}, {"spotifyInfo": {"title": "Hard to Be a Girl", "artist": "Adam Green", "time": 101480, "min": 1, "sec": 41}, "youtubeInfo": {"id": "/watch?v=22hrKu7dz44", "URL": "https://www.youtube.com//watch?v=22hrKu7dz44", "title": "ADAM GREEN HARD TO BE A GIRL"}}, {"spotifyInfo": {"title": "Imogen", "artist": "Nick Mulvey", "time": 255533, "min": 4, "sec": 15}, "youtubeInfo": {"id": "/watch?v=_TZ4T9PaZLk", "URL": "https://www.youtube.com//watch?v=_TZ4T9PaZLk", "title": "Nick Mulvey - Imogen"}}, {"spotifyInfo": {"title": "Ce n'est rien", "artist": "Julien Clerc", "time": 214173, "min": 3, "sec": 34}, "youtubeInfo": {"id": "/watch?v=ZzQ403SHTPM", "URL": "https://www.youtube.com//watch?v=ZzQ403SHTPM", "title": "Julien Clerc - Ce N'est Rien"}}, {"spotifyInfo": {"title": "Marie Jeanne", "artist": "Kacem Wapalek", "time": 159073, "min": 2, "sec": 39}, "youtubeInfo": {"id": "/watch?v=zO7SNthq89M", "URL": "https://www.youtube.com//watch?v=zO7SNthq89M", "title": "Kacem Wapalek Marie Jeanne"}}, {"spotifyInfo": {"title": "Vingt sur vingt", "artist": "Kacem Wapalek", "time": 250784, "min": 4, "sec": 10}, "youtubeInfo": {"id": "/watch?v=pJVvbTAx8_Y", "URL": "https://www.youtube.com//watch?v=pJVvbTAx8_Y", "title": "Kacem Wapalek - Vingt sur vingt"}}, {"spotifyInfo": {"title": "While My Guitar Gently Weeps - Esher Demo", "artist": "The Beatles", "time": 161440, "min": 2, "sec": 41}, "youtubeInfo": {"id": "/watch?v=qV-VSV0Utig", "URL": "https://www.youtube.com//watch?v=qV-VSV0Utig", "title": "The Beatles - While My Guitar Gently Weeps (Esher Demo / Audio)"}}, {"spotifyInfo": {"title": "Je suis un voyou", "artist": "Georges Brassens", "time": 158440, "min": 2, "sec": 38}, "youtubeInfo": {"id": "/watch?v=prdS6mw9s40", "URL": "https://www.youtube.com//watch?v=prdS6mw9s40", "title": "Georges Brassens - Je suis un voyou"}}, {"spotifyInfo": {"title": "Abusey Junction", "artist": "KOKOROKO", "time": 424080, "min": 7, "sec": 4}, "youtubeInfo": {"id": "/watch?v=tSv04ylc6To", "URL": "https://www.youtube.com//watch?v=tSv04ylc6To", "title": "KOKOROKO - ABUSEY JUNCTION // WE OUT HERE"}}, {"spotifyInfo": {"title": "P... de toi", "artist": "Georges Brassens", "time": 160493, "min": 2, "sec": 40}, "youtubeInfo": {"id": "/watch?v=r92iG61uNgI", "URL": "https://www.youtube.com//watch?v=r92iG61uNgI", "title": "George Brassens - Putain De Toi"}}, {"spotifyInfo": {"title": "Le m\u00e9t\u00e8que", "artist": "Georges Moustaki", "time": 150440, "min": 2, "sec": 30}, "youtubeInfo": {"id": "/watch?v=MV8fGf-N06A", "URL": "https://www.youtube.com//watch?v=MV8fGf-N06A", "title": "Georges Moustaki - Le M\u00e9t\u00e8que"}}, {"spotifyInfo": {"title": "Le temps de l'amour - Fox Medium", "artist": "Fran\u00e7oise Hardy", "time": 144826, "min": 2, "sec": 24}, "youtubeInfo": {"id": "/watch?v=v1Kv7aq40iI", "URL": "https://www.youtube.com//watch?v=v1Kv7aq40iI", "title": "Le Temps De L'amour (Fox Medium)"}}, {"spotifyInfo": {"title": "Ma solitude", "artist": "Georges Moustaki", "time": 176866, "min": 2, "sec": 56}, "youtubeInfo": {"id": "/watch?v=h9-OzSzCDWo", "URL": "https://www.youtube.com//watch?v=h9-OzSzCDWo", "title": "Georges Moustaki - Ma solitude (1970)"}}, {"spotifyInfo": {"title": "Thunderclouds", "artist": "Sia", "time": 187026, "min": 3, "sec": 7}, "youtubeInfo": {"id": "/watch?v=kg1BljLu9YY", "URL": "https://www.youtube.com//watch?v=kg1BljLu9YY", "title": "LSD - Thunderclouds (Official Video) ft. Sia, Diplo, Labrinth"}}, {"spotifyInfo": {"title": "Song for Elias", "artist": "The Cat Empire", "time": 272666, "min": 4, "sec": 32}, "youtubeInfo": {"id": "/watch?v=W-P7L7YAUF0", "URL": "https://www.youtube.com//watch?v=W-P7L7YAUF0", "title": "The Cat Empire - Song For Elias (Official Audio)"}}, {"spotifyInfo": {"title": "Miserere", "artist": "The Cat Empire", "time": 399053, "min": 6, "sec": 39}, "youtubeInfo": {"id": "/watch?v=xx3Dc5tUD8o", "URL": "https://www.youtube.com//watch?v=xx3Dc5tUD8o", "title": "The Cat Empire - Miserere (Official Audio)"}}, {"spotifyInfo": {"title": "Les Hautes lumi\u00e8res", "artist": "Fauve", "time": 307813, "min": 5, "sec": 7}, "youtubeInfo": {"id": "/watch?v=wDxchoqHQbg", "URL": "https://www.youtube.com//watch?v=wDxchoqHQbg", "title": "FAUVE \u2260 LES HAUTES LUMI\u00c8RES"}}, {"spotifyInfo": {"title": "Jalousie", "artist": "Ang\u00e8le", "time": 225706, "min": 3, "sec": 45}, "youtubeInfo": {"id": null, "URL": "#", "title": "NaN"}}, {"spotifyInfo": {"title": "Trop beau", "artist": "Lomepal", "time": 244586, "min": 4, "sec": 4}, "youtubeInfo": {"id": "/watch?v=Bkm03KcnKHE", "URL": "https://www.youtube.com//watch?v=Bkm03KcnKHE", "title": "Lomepal - Trop beau (Clip officiel)"}}, {"spotifyInfo": {"title": "Somehow", "artist": "Toun-e", "time": 166844, "min": 2, "sec": 46}, "youtubeInfo": {"id": "/watch?v=OpEhwij6g5A", "URL": "https://www.youtube.com//watch?v=OpEhwij6g5A", "title": "Somehow"}}, {"spotifyInfo": {"title": "God Only Knows", "artist": "Adem", "time": 154746, "min": 2, "sec": 34}, "youtubeInfo": {"id": "/watch?v=Kf9UHKYEBGQ", "URL": "https://www.youtube.com//watch?v=Kf9UHKYEBGQ", "title": "God Only Knows"}}, {"spotifyInfo": {"title": "Bang Bang", "artist": "Dalida", "time": 204733, "min": 3, "sec": 24}, "youtubeInfo": {"id": "/watch?v=69U41WklpbI", "URL": "https://www.youtube.com//watch?v=69U41WklpbI", "title": "Dalida - Bang Bang"}}, {"spotifyInfo": {"title": "Les gitans", "artist": "Mano Solo", "time": 289440, "min": 4, "sec": 49}, "youtubeInfo": {"id": "/watch?v=xzk3HQ75tEc", "URL": "https://www.youtube.com//watch?v=xzk3HQ75tEc", "title": "Mano Solo - Les Gitans"}}, {"spotifyInfo": {"title": "The Old Man", "artist": "Yom", "time": 313080, "min": 5, "sec": 13}, "youtubeInfo": {"id": "/watch?v=0AUPziUaoeM", "URL": "https://www.youtube.com//watch?v=0AUPziUaoeM", "title": "The Old Man"}}, {"spotifyInfo": {"title": "Barbara / Arr Tharaud: Du bout des l\u00e8vres (Arr. Tharaud for Piano & Keyboards)", "artist": "Barbara", "time": 128493, "min": 2, "sec": 8}, "youtubeInfo": {"id": "/watch?v=UDRusD5BtcU", "URL": "https://www.youtube.com//watch?v=UDRusD5BtcU", "title": "Du bout des l\u00e8vres (Arr. Tharaud for Piano & Keyboards)"}}, {"spotifyInfo": {"title": "Scenic World", "artist": "Dom La Nena", "time": 145607, "min": 2, "sec": 25}, "youtubeInfo": {"id": "/watch?v=p2ooBKyXSQE", "URL": "https://www.youtube.com//watch?v=p2ooBKyXSQE", "title": "DOM LA NENA - SCENIC WORLD"}}, {"spotifyInfo": {"title": "Baila Leila", "artist": "Goran Bregovi\u0107", "time": 279026, "min": 4, "sec": 39}, "youtubeInfo": {"id": "/watch?v=-3W3YpLrlIU", "URL": "https://www.youtube.com//watch?v=-3W3YpLrlIU", "title": "Goran Bregovic  - Baila Leila - ( Official  Audio 2018 ) HD"}}, {"spotifyInfo": {"title": "Let Me Down Slowly", "artist": "Alec Benjamin", "time": 169353, "min": 2, "sec": 49}, "youtubeInfo": {"id": "/watch?v=50VNCymT-Cs", "URL": "https://www.youtube.com//watch?v=50VNCymT-Cs", "title": "Alec Benjamin - Let Me Down Slowly [Official Music Video]"}}, {"spotifyInfo": {"title": "Medley t\u00e9sey", "artist": "Seyt\u00e9", "time": 428328, "min": 7, "sec": 8}, "youtubeInfo": {"id": null, "URL": "#", "title": "NaN"}}, {"spotifyInfo": {"title": "Gloria", "artist": "Jain", "time": 167280, "min": 2, "sec": 47}, "youtubeInfo": {"id": "/watch?v=6P_7vlJHfak", "URL": "https://www.youtube.com//watch?v=6P_7vlJHfak", "title": "Gloria"}}, {"spotifyInfo": {"title": "Dream", "artist": "Jain", "time": 185186, "min": 3, "sec": 5}, "youtubeInfo": {"id": "/watch?v=VjLuUx3e0gE", "URL": "https://www.youtube.com//watch?v=VjLuUx3e0gE", "title": "Jain - Dream (Official Lyric Video)"}}, {"spotifyInfo": {"title": "Voyage en Italie", "artist": "Lilicub", "time": 235466, "min": 3, "sec": 55}, "youtubeInfo": {"id": "/watch?v=bse02AUNP_o", "URL": "https://www.youtube.com//watch?v=bse02AUNP_o", "title": "Lilicub - Voyage En Italie"}}, {"spotifyInfo": {"title": "Elephant Gun", "artist": "Beirut", "time": 348893, "min": 5, "sec": 48}, "youtubeInfo": {"id": "/watch?v=SWSz_PAfgNc", "URL": "https://www.youtube.com//watch?v=SWSz_PAfgNc", "title": "Beirut - Elephant Gun (Official Video)"}}, {"spotifyInfo": {"title": "Valse No. 2 de Chostakovitch", "artist": "Versaillesstation", "time": 138483, "min": 2, "sec": 18}, "youtubeInfo": {"id": "/watch?v=AQYnEHE9A6s", "URL": "https://www.youtube.com//watch?v=AQYnEHE9A6s", "title": "Valse No. 2 de Chostakovitch"}}, {"spotifyInfo": {"title": "All in You (feat. Anna Kova)", "artist": "Synapson", "time": 257971, "min": 4, "sec": 17}, "youtubeInfo": {"id": "/watch?v=tvMoteOdPBA", "URL": "https://www.youtube.com//watch?v=tvMoteOdPBA", "title": "Synapson - All in You feat. Anna Kova (Official Music Video)"}}, {"spotifyInfo": {"title": "Mala Vida", "artist": "Nouvelle Vague", "time": 218666, "min": 3, "sec": 38}, "youtubeInfo": {"id": "/watch?v=U_PprMPJ1LU", "URL": "https://www.youtube.com//watch?v=U_PprMPJ1LU", "title": "Nouvelle Vague - Mala Vida (avec Olivia Ruiz)"}}, {"spotifyInfo": {"title": "La mer", "artist": "Charles Trenet", "time": 201840, "min": 3, "sec": 21}, "youtubeInfo": {"id": "/watch?v=fztkUuunI7g", "URL": "https://www.youtube.com//watch?v=fztkUuunI7g", "title": "Charles Trenet - La Mer"}}, {"spotifyInfo": {"title": "Junior suite", "artist": "Vanessa Paradis", "time": 209986, "min": 3, "sec": 29}, "youtubeInfo": {"id": "/watch?v=d21UT31QiLk", "URL": "https://www.youtube.com//watch?v=d21UT31QiLk", "title": "Junior suite"}}, {"spotifyInfo": {"title": "Sunshine", "artist": "Mos Def", "time": 265786, "min": 4, "sec": 25}, "youtubeInfo": {"id": "/watch?v=IMOy9SsUQ7U", "URL": "https://www.youtube.com//watch?v=IMOy9SsUQ7U", "title": "Mos Def- Sunshine"}}, {"spotifyInfo": {"title": "Loco Contigo (feat. J. Balvin & Tyga)", "artist": "DJ Snake", "time": 185194, "min": 3, "sec": 5}, "youtubeInfo": {"id": null, "URL": "#", "title": "NaN"}}, {"spotifyInfo": {"title": "Le petit pain au chocolat", "artist": "Joe Dassin", "time": 205626, "min": 3, "sec": 25}, "youtubeInfo": {"id": "/watch?v=FaswDILZU8c", "URL": "https://www.youtube.com//watch?v=FaswDILZU8c", "title": "Joe Dassin Le petit pain au chocolat 1969.avi"}}]}